README.md
setup.cfg
setup.py
epfl_ldap.egg-info/PKG-INFO
epfl_ldap.egg-info/SOURCES.txt
epfl_ldap.egg-info/dependency_links.txt
epfl_ldap.egg-info/requires.txt
epfl_ldap.egg-info/top_level.txt
epflldap/__init__.py
epflldap/ldap_authenticate.py
epflldap/ldap_search.py
epflldap/settings.py
epflldap/utils.py
epflldap/test/__init__.py
epflldap/test/test_ldap_authenticate.py
epflldap/test/test_ldap_mock.py
epflldap/test/test_ldap_search.py