Metadata-Version: 1.1
Name: epfl-ldap
Version: 0.0.6
Summary: A simple package to interact with the EPFL LDAP
Home-page: https://github.com/epfl-idevelop/epfl-ldap
Author: Charmier Grégory
Author-email: gregory.charmier@epfl.ch
License: MIT
Keywords: EPFL development LDAP search authenticate
Platform: UNKNOWN
Classifier: Development Status :: 3 - Alpha
Classifier: Intended Audience :: Developers
Classifier: Topic :: Software Development :: Build Tools
Classifier: License :: OSI Approved :: MIT License
Classifier: Programming Language :: Python
Classifier: Programming Language :: Python :: 2
Classifier: Programming Language :: Python :: 2.7
Classifier: Programming Language :: Python :: 3
Classifier: Programming Language :: Python :: 3.5
